{"DefaultCulture":"en","Cultures":["en","nl","fr","de"],"Resources":{"PageHead":[{"ForPath":"/Local/Da/","SubstitutionFields":null,"Values":{"en":"\u003Ch1\u003ELocalization Test 2\u003C/h1\u003E","nl":"\u003Ch1\u003ELokalisatietest 2\u003C/h1\u003E","fr":"\u003Ch1\u003ETest de localisation 2\u003C/h1\u003E","de":"\u003Ch1\u003ELokalisierungstest 2\u003C/h1\u003E"}},{"ForPath":"/Pages/","SubstitutionFields":null,"Values":{"en":"\u003Ch1\u003ELocalized Page\u003C/h1\u003E","nl":"\u003Ch1\u003EGelokaliseerde pagina\u003C/h1\u003E","fr":"\u003Ch1\u003EPage localis\u00E9e\u003C/h1\u003E","de":"\u003Ch1\u003ELokalisierte Seite\u003C/h1\u003E"}},{"ForPath":"/Local/","SubstitutionFields":null,"Values":{"en":"\u003Ch1\u003ELocalization Test 1\u003C/h1\u003E","nl":"\u003Ch1\u003ELokalisatietest 1\u003C/h1\u003E","fr":"\u003Ch1\u003ETest de localisation 1\u003C/h1\u003E","de":"\u003Ch1\u003ELokalisierungstest 1\u003C/h1\u003E"}},{"ForPath":null,"SubstitutionFields":null,"Values":{"en":"","nl":"","fr":"","de":""}}],"NotEnoughTimeSpan":[{"ForPath":null,"SubstitutionFields":null,"Values":{"en":"Please select titles that are more spread over time.","nl":"Selecteer titels die meer verspreid zijn over de tijd.","fr":"Veuillez s\u00E9lectionner des titres plus \u00E9tal\u00E9s dans le temps.","de":"Bitte w\u00E4hlen Sie Titel aus, die \u00FCber die Zeit verteilter sind."}}],"Localization Test":[{"ForPath":null,"SubstitutionFields":null,"Values":{"en":"Localization Test","nl":"Localizatie Test","fr":"Test de Localization"}}],"This is a short name for {0}.":[{"ForPath":null,"SubstitutionFields":null,"Values":{"en":"This is a short name for {0}.","nl":"Dit is een korte naam voor {0}.","fr":"Il s\u2019agit d\u2019un nom abr\u00E9g\u00E9 pour {0}.","de":"Dies ist ein Kurzname f\u00FCr {0}."}}],"This is a \u003Ci\u003Eshort\u003C/i\u003E name for \u003Cb\u003E{0}\u003C/b\u003E.":[{"ForPath":null,"SubstitutionFields":null,"Values":{"en":"This is a \u003Ci\u003Eshort\u003C/i\u003E name for \u003Cb\u003E{0}\u003C/b\u003E.","nl":"Dit is een \u003Ci\u003Ekorte\u003C/i\u003E naam voor \u003Cb\u003E{0}\u003C/b\u003E.","fr":"Il s\u2019agit d\u2019un nom \u003Ci\u003Eabr\u00E9g\u00E9\u003C/i\u003E pour \u003Cb\u003E{0}\u003C/b\u003E.","de":"Dies ist ein \u003Ci\u003EKurzname\u003C/i\u003E f\u00FCr \u003Cb\u003E{0}\u003C/b\u003E."}}],"Following errors have occured:":[{"ForPath":null,"SubstitutionFields":null,"Values":{"en":"Following errors have occured:","nl":"De volgende fouten zijn opgetreden:","fr":"Les erreurs suivantes se sont produites :"}}],"Name":[{"ForPath":null,"SubstitutionFields":null,"Values":{"en":"Name","nl":"Naam","fr":"Nom","de":"Name"}}],"Submit":[{"ForPath":null,"SubstitutionFields":null,"Values":{"en":"Submit","nl":"Opslaan","fr":"Envoyer","de":"Senden"}}],"Sorry! The {0} is required...":[{"ForPath":null,"SubstitutionFields":null,"Values":{"en":"Sorry! The {0} is required...","nl":"Sorry! {0} is verplicht...","fr":"D\u00E9sol\u00E9! {0} est obligatoire...","de":"Tut mir Leid! {0} ist erforderlich..."}}],"ZipCode":[{"ForPath":null,"SubstitutionFields":null,"Values":{"en":"Zip code","nl":"Postcode","fr":"Code postale"}}],"PageFoot":[{"ForPath":null,"SubstitutionFields":["{{culture:name}}"],"Values":{"en":"\u003Cp\u003ECurrent UI Culture: {{culture:name}}\u003C/p\u003E","nl":"\u003Cp\u003EHuidige UI-cultuur: {{culture:name}}\u003C/p\u003E","fr":"\u003Cp\u003ECulture actuelle de l\u2019interface utilisateur : {{culture:name}}\u003C/p\u003E","de":"\u003Cp\u003EAktuelle UI-Kultur: {{culture:name}}\u003C/p\u003E"}}],"Age":[{"ForPath":null,"SubstitutionFields":null,"Values":{"en":"Age","nl":"Leeftijd","fr":"\u00C2ge","de":"Alter"}}],"Please validate this before end":[{"ForPath":null,"SubstitutionFields":["{{view:Date.Year:#,##0}}"],"Values":{"en":"Please validate this before end of {{view:Date.Year:#,##0}}","nl":"Valideer dit voor het einde van {{view:Date.Year:#,##0}}","fr":"Veuillez valider cela avant la fin de {{view:Date.Year:#,##0}}","de":"Bitte \u00FCberpr\u00FCfen Sie dies vor dem Ende von {{view:Date.Year:#,##0}}"}}],"LongText2":[{"ForPath":null,"SubstitutionFields":null,"Values":{"en":"\u003Ch1\u003EThis is some longer text\u003C/h1\u003E\r\n\u003Cp\u003ENow we can write on multiple lines.\u003C/p\u003E\r\n\u003Cp\u003EAs we do here, we write long paragraphs of text that do not fit on a single line but flow over multiple lines so that the textarea needs to grow.\u003C/p\u003E\r\n4\r\n5\r\n6\r\n7\r\n8\r\n9\r\n10\r\n11\r\n12\r\n13\r\n14\r\n15\r\n\u003Ci\u003EMe.\u003C/i\u003E"}}],"Do you also live in {{localizer:CountryBE}} ?":[{"ForPath":null,"SubstitutionFields":["{{localizer:CountryBE}}"],"Values":{"en":"Do you also live in {{localizer:CountryBE}} ?","nl":"Woont u ook in {{localizer:CountryBE}} ?","fr":"Habitez-vous aussi en {{localizer:CountryBE}} ?","de":"Wohnst du auch in {{localizer:CountryBE}} ?"}}],"CountryBE":[{"ForPath":null,"SubstitutionFields":null,"Values":{"en":"Belgium","fr":"Belgique","nl":"Belgi\u00EB"}}],"CountryFR":[{"ForPath":null,"SubstitutionFields":null,"Values":{"en":"France","fr":"France","nl":"Frankrijk"}}],"CountryNL":[{"ForPath":null,"SubstitutionFields":null,"Values":{"en":"Netherlands","fr":"Pays-Bas","nl":"Nederland"}}],"The value \u0027{0}\u0027 is not valid for {1}.":[{"ForPath":null,"SubstitutionFields":null,"Values":{"en":"The value \u0027{0}\u0027 is not valid for {1}.","nl":"De waarde \u0027{0}\u0027 geldt niet voor {1}.","fr":"La valeur \u0027{0}\u0027 n\u2019est pas valide pour {1}.","de":"Der Wert \u0027{0}\u0027 gilt nicht f\u00FCr {1}."}}],"A value for the \u0027{0}\u0027 property was not provided.":[{"ForPath":null,"SubstitutionFields":null,"Values":{"en":"A value for the \u0027{0}\u0027 property was not provided.","nl":"Een waarde voor het onroerend goed \u0027{0}\u0027 werd niet verstrekt.","fr":"Aucune valeur pour la propri\u00E9t\u00E9 \u00AB {0} \u00BB n\u2019a \u00E9t\u00E9 fournie.","de":"Ein Wert f\u00FCr die Eigenschaft \u0027{0}\u0027 wurde nicht angegeben."}}],"The field {0} must be a number.":[{"ForPath":null,"SubstitutionFields":null,"Values":{"en":"The field {0} must be a number.","nl":"Het veld {0} moet een getal zijn.","fr":"Le champ {0} doit \u00EAtre un nombre.","de":"Das Feld {0} muss eine Zahl sein."}}],"The value \u0027{0}\u0027 is invalid.":[{"ForPath":null,"SubstitutionFields":null,"Values":{"en":"The value \u0027{0}\u0027 is invalid.","nl":"De waarde \u0027{0}\u0027 is ongeldig.","fr":"La valeur \u0027{0}\u0027 n\u2019est pas valide.","de":"Der Wert \u0027{0}\u0027 ist ung\u00FCltig."}}],"A value is required.":[{"ForPath":null,"SubstitutionFields":null,"Values":{"en":"A value is required.","nl":"Er is een waarde vereist.","fr":"Une valeur est requise.","de":"Ein Wert ist erforderlich."}}],"The supplied value is invalid for {0}.":[{"ForPath":null,"SubstitutionFields":null,"Values":{"en":"The supplied value is invalid for {0}.","nl":"De opgegeven waarde is ongeldig voor {0}.","fr":"La valeur fournie n\u2019est pas valide pour {0}.","de":"Der angegebene Wert ist f\u00FCr {0} ung\u00FCltig."}}],"The value \u0027{0}\u0027 is not valid.":[{"ForPath":null,"SubstitutionFields":null,"Values":{"en":"The value \u0027{0}\u0027 is not valid.","nl":"De waarde \u0027{0}\u0027 is niet geldig.","fr":"La valeur \u0027{0}\u0027 n\u2019est pas valide.","de":"Der Wert \u0027{0}\u0027 ist ung\u00FCltig."}}],"The supplied value is invalid.":[{"ForPath":null,"SubstitutionFields":null,"Values":{"en":"The supplied value is invalid.","nl":"De opgegeven waarde is ongeldig.","fr":"La valeur fournie n\u2019est pas valide.","de":"Der angegebene Wert ist ung\u00FCltig."}}],"The field must be a number.":[{"ForPath":null,"SubstitutionFields":null,"Values":{"en":"The field must be a number.","nl":"Het veld moet een getal zijn.","fr":"Le champ doit \u00EAtre un nombre.","de":"Das Feld muss eine Zahl sein."}}],"A non-empty request body is required.":[{"ForPath":null,"SubstitutionFields":null,"Values":{"en":"A non-empty request body is required.","nl":"Een niet-lege aanvraagtekst is vereist.","fr":"Un corps de demande non vide est requis.","de":"Ein nicht leerer Anforderungstext ist erforderlich."}}],"\u0027{0}\u0027 and \u0027{1}\u0027 do not match.":[{"ForPath":null,"SubstitutionFields":null,"Values":{"en":"\u0027{0}\u0027 and \u0027{1}\u0027 do not match.","nl":"\u0027{0}\u0027 en \u0027{1}\u0027 komen niet overeen.","fr":"\u00AB {0} \u00BB et \u00AB {1} \u00BB ne correspondent pas.","de":"\u0022{0}\u0022 und \u0022{1}\u0022 stimmen nicht \u00FCberein."}}],"The {0} field is not a valid credit card number.":[{"ForPath":null,"SubstitutionFields":null,"Values":{"en":"The {0} field is not a valid credit card number.","nl":"Het veld {0} is geen geldig creditcardnummer.","fr":"Le champ {0} n\u2019est pas un num\u00E9ro de carte de cr\u00E9dit valide.","de":"Das Feld {0} ist keine g\u00FCltige Kreditkartennummer."}}],"{0} is not valid.":[{"ForPath":null,"SubstitutionFields":null,"Values":{"en":"{0} is not valid.","nl":"{0} is niet geldig.","fr":"{0} n\u2019est pas valide.","de":"{0} ist ung\u00FCltig."}}],"The {0} field is not a valid e-mail address.":[{"ForPath":null,"SubstitutionFields":null,"Values":{"en":"The {0} field is not a valid e-mail address.","nl":"Het veld {0} is geen geldig e-mailadres.","fr":"Le champ {0} n\u2019est pas une adresse e-mail valide.","de":"Das Feld {0} ist keine g\u00FCltige E-Mail-Adresse."}}],"The {0} field only accepts files with the following extensions: {1}":[{"ForPath":null,"SubstitutionFields":null,"Values":{"en":"The {0} field only accepts files with the following extensions: {1}","nl":"Het veld {0} accepteert alleen bestanden met de volgende extensies: {1}","fr":"Le champ {0} accepte uniquement les fichiers portant les extensions suivantes : {1}","de":"Das Feld {0} akzeptiert nur Dateien mit den folgenden Erweiterungen: {1}"}}],"The field {0} must be a string or array type with a maximum length of \u0027{1}\u0027.":[{"ForPath":null,"SubstitutionFields":null,"Values":{"en":"The field {0} must be a string or array type with a maximum length of \u0027{1}\u0027.","nl":"Het veld {0} moet een tekenreeks of arraytype zijn met een maximale lengte van \u0027{1}\u0027.","fr":"Le champ {0} doit \u00EAtre de type cha\u00EEne ou tableau d\u2019une longueur maximale de \u0027{1}\u0027.","de":"Das Feld {0} muss ein Zeichenfolgen- oder Arraytyp mit einer maximalen L\u00E4nge von \u0027{1}\u0027 sein."}}],"The field {0} must be a string or array type with a minimum length of \u0027{1}\u0027.":[{"ForPath":null,"SubstitutionFields":null,"Values":{"en":"The field {0} must be a string or array type with a minimum length of \u0027{1}\u0027.","nl":"Het veld {0} moet een tekenreeks of arraytype zijn met een minimale lengte van \u0027{1}\u0027.","fr":"Le champ {0} doit \u00EAtre de type cha\u00EEne ou tableau d\u2019une longueur minimale de \u0027{1}\u0027.","de":"Das Feld {0} muss ein Zeichenfolgen- oder Arraytyp mit einer Mindestl\u00E4nge von \u0027{1}\u0027 sein."}}],"The {0} field is not a valid phone number.":[{"ForPath":null,"SubstitutionFields":null,"Values":{"en":"The {0} field is not a valid phone number.","nl":"Het veld {0} is geen geldig telefoonnummer.","fr":"Le champ {0} n\u2019est pas un num\u00E9ro de t\u00E9l\u00E9phone valide.","de":"Das Feld {0} ist keine g\u00FCltige Telefonnummer."}}],"The field {0} must be between {1} and {2}.":[{"ForPath":null,"SubstitutionFields":null,"Values":{"en":"The field {0} must be between {1} and {2}.","nl":"Het veld {0} moet tussen {1} en {2} liggen.","fr":"Le champ {0} doit se situer entre {1} et {2}.","de":"Das Feld {0} muss zwischen {1} und {2} liegen."}}],"The field {0} must match the regular expression \u0027{1}\u0027.":[{"ForPath":null,"SubstitutionFields":null,"Values":{"en":"The field {0} must match the regular expression \u0027{1}\u0027.","nl":"Het veld {0} moet overeenkomen met de reguliere uitdrukking \u0027{1}\u0027.","fr":"Le champ {0} doit correspondre \u00E0 l\u2019expression r\u00E9guli\u00E8re \u00AB\u00A0{1}\u00A0\u00BB.","de":"Das Feld {0} muss mit dem regul\u00E4ren Ausdruck \u0027{1}\u0027 \u00FCbereinstimmen."}}],"The {0} field is required.":[{"ForPath":null,"SubstitutionFields":null,"Values":{"en":"The {0} field is required.","nl":"Het {0} veld is verplicht.","fr":"Le champ {0} est obligatoire.","de":"Das Feld {0} ist erforderlich."}}],"The field {0} must be a string with a maximum length of {1}.":[{"ForPath":null,"SubstitutionFields":null,"Values":{"en":"The field {0} must be a string with a maximum length of {1}.","nl":"Het veld {0} moet een tekenreeks zijn met een maximale lengte van {1}.","fr":"Le champ {0} doit \u00EAtre une cha\u00EEne d\u2019une longueur maximale de {1}.","de":"Das Feld {0} muss eine Zeichenfolge mit einer maximalen L\u00E4nge von {1} sein."}}],"The field {0} must be a string with a minimum length of {1} and a maximum length of {2}.":[{"ForPath":null,"SubstitutionFields":null,"Values":{"en":"The field {0} must be a string with a minimum length of {1} and a maximum length of {2}.","nl":"Het veld {0} moet een tekenreeks zijn met een minimale lengte van {1} en een maximale lengte van {2}.","fr":"Le champ {0} doit \u00EAtre une cha\u00EEne d\u2019une longueur minimale de {1} et d\u2019une longueur maximale de {2}.","de":"Das Feld {0} muss eine Zeichenfolge mit einer Mindestl\u00E4nge von {1} und einer maximalen L\u00E4nge von {2} sein."}}],"The {0} field is not a valid fully-qualified http, https, or ftp URL.":[{"ForPath":null,"SubstitutionFields":null,"Values":{"en":"The {0} field is not a valid fully-qualified http, https, or ftp URL.","nl":"Het veld {0} is geen geldige, volledig gekwalificeerde http-, https- of ftp-URL.","fr":"Le champ {0} n\u2019est pas une URL http, https ou ftp compl\u00E8te valide.","de":"Das Feld {0} ist keine g\u00FCltige, vollqualifizierte http-, https- oder ftp-URL."}}],"The field {0} is invalid.":[{"ForPath":null,"SubstitutionFields":null,"Values":{"en":"The field {0} is invalid.","nl":"Het veld {0} is ongeldig.","fr":"Le champ {0} n\u2019est pas valide.","de":"Das Feld {0} ist ung\u00FCltig."}}],"Yes":[{"ForPath":null,"SubstitutionFields":null,"Values":{"en":"Yes","nl":"Ja","fr":"Oui","de":"Ja"}}],"No":[{"ForPath":null,"SubstitutionFields":null,"Values":{"en":"No","nl":"Neen","fr":"Non","de":"Nein"}}],"Cancel":[{"ForPath":null,"SubstitutionFields":null,"Values":{"en":"Cancel","nl":"Annuleren","fr":"Annuler","de":"Abbrechen"}}],"OK":[{"ForPath":null,"SubstitutionFields":null,"Values":{"en":"OK","nl":"OK","fr":"OK","de":"OK"}}]}}